wearcheck/__init__.py
wearcheck/main.py
wearcheck/test_part/sample_part.step
wearcheck-0.1.0.dist-info/licenses/LICENSE
wearcheck-0.1.0.dist-info/METADATA
wearcheck-0.1.0.dist-info/WHEEL
wearcheck-0.1.0.dist-info/entry_points.txt
wearcheck-0.1.0.dist-info/top_level.txt
wearcheck-0.1.0.dist-info/RECORD
