Metadata-Version: 2.4
Name: wearcheck
Version: 0.1.0
Summary: CLI tool for estimating and visualising mechanical wear
Author-email: Dmytro Tkachivskyi <dmtkac@proton.me>
License-Expression: MIT
Requires-Python: >=3.9
License-File: LICENSE
Requires-Dist: numpy
Requires-Dist: trimesh
Requires-Dist: pyvista
Requires-Dist: rtree
Requires-Dist: scipy
Dynamic: license-file
